Metadata-Version: 2.1
Name: limewrkpi
Version: 2.1.3
Author: Kenny
Requires-Python: >=3.10
Requires-Dist: requests
Requires-Dist: pandas==1.5.3
Requires-Dist: cython
Requires-Dist: ftfy
Requires-Dist: keyrings.google.artifactregistry-auth
Requires-Dist: cryptography<=42.0.8
